mailcom/__init__.py
mailcom/inout.py
mailcom/parse.py
mailcom/test/test_parse.py
mailcom-0.0.1.dist-info/METADATA
mailcom-0.0.1.dist-info/WHEEL
mailcom-0.0.1.dist-info/licenses/LICENSE
mailcom-0.0.1.dist-info/RECORD
