Metadata-Version: 2.3
Name: mailcom
Version: 0.0.1
Summary: Pseudonymize email content in Romance languages
Project-URL: Homepage, https://github.com/ssciwr/mailcom
Project-URL: Issues, https://github.com/ssciwr/mailcom/issues
Author-email: Inga Ulusoy <ssc@iwr.uni-heidelberg.de>, Thore Olthoff <ssc@iwr.uni-heidelberg.de>
License: MIT License
License-File: LICENSE
Classifier: License :: OSI Approved :: MIT License
Classifier: Operating System :: OS Independent
Classifier: Programming Language :: Python :: 3
Requires-Python: >=3.8
Requires-Dist: spacy
Requires-Dist: transformers
Provides-Extra: dev
Requires-Dist: pre-commit; extra == 'dev'
Requires-Dist: pytest; extra == 'dev'
